verilog/decoder/mux41.v
module mux41(
    input [0:3] I,
    input [1:0] S,
    output y
    );

	assign y = ~S[1]&~S[0]&I[0] | ~S[1]&S[0]&I[1] | S[1]&~S[0]&I[2] | S[1]&S[0]&I[3];

endmodule

verilog/decoder/decoder.v
module decoder(
    input [3:0] C,
    output [3:0] y
    );
	
	mux41 M0({1'b1,1'b0,1'b1,1'b0}, C[1:0], y[0]);
	mux41 M1({~C[3], 1'b0, C[3]&~C[2], 1'b1}, C[1:0], y[1]);
	mux41 M2({~C[3], C[3]&~C[2], ~C[3]&~C[2], ~C[3]}, C[1:0], y[2]);
	mux41 M3({1'b0, ~C[3]&C[2], ~C[3]&C[2], 1'b0}, C[1:0], y[3]);

endmodule

ece/verilog/decoder/decoder_t.v
module decoder_t;

	// Inputs
	reg [3:0] C;

	// Outputs
	wire [3:0] y;

	// Instantiate the Unit Under Test (UUT)
	decoder uut (
		.C(C), 
		.y(y)
	);

	initial begin

       $dumpfile("test.vcd");
       $dumpvars(0,decoder_t);
		C = 4'b1101;
		#1;

		C = 4'b1100;
		#1;

		C = 4'b1011;
		#1;

		C = 4'b1010;
		#1;
		
		C = 4'b1001;
		#1;

		C = 4'b0010;
		#1;
		
		C = 4'b0011;
		#1;
		
		C = 4'b0100;
		#1;
		
		C = 4'b0101;
		#1;
		
		C = 4'b0110;
		#1;


	   

	end

    initial
    begin
       $monitor("At time %t, C = %b,  y = %b", $time, C , y); 
    end     
endmodule

ece/verilog/decoder/test.vcd
$date
	Sun Oct  9 02:21:34 2016
$end
$version
	Icarus Verilog
$end
$timescale
	1s
$end
$scope module decoder_t $end
$var wire 4 ! y [3:0] $end
$var reg 4 " C [3:0] $end
$scope module uut $end
$var wire 4 # C [3:0] $end
$var wire 4 $ y [3:0] $end
$scope module M0 $end
$var wire 4 % I [0:3] $end
$var wire 2 & S [1:0] $end
$var wire 1 ' y $end
$upscope $end
$scope module M1 $end
$var wire 4 ( I [0:3] $end
$var wire 2 ) S [1:0] $end
$var wire 1 * y $end
$upscope $end
$scope module M2 $end
$var wire 4 + I [0:3] $end
$var wire 2 , S [1:0] $end
$var wire 1 - y $end
$upscope $end
$scope module M3 $end
$var wire 4 . I [0:3] $end
$var wire 2 / S [1:0] $end
$var wire 1 0 y $end
$upscope $end
$upscope $end
$upscope $end
$enddefinitions $end
#0
$dumpvars
00
b1 /
b0 .
0-
b1 ,
b0 +
0*
b1 )
b1 (
0'
b1 &
b1010 %
b0 $
b1101 #
b1101 "
b0 !
$end
#1
b1 !
b1 $
1'
b0 &
b0 )
b0 ,
b0 /
b1100 "
b1100 #
#2
0'
b10 !
b10 $
1*
b11 (
b100 +
b11 &
b11 )
b11 ,
b11 /
b1011 "
b1011 #
#3
1'
b11 !
b11 $
1*
b10 &
b10 )
b10 ,
b10 /
b1010 "
b1010 #
#4
1-
0'
b100 !
b100 $
0*
b1 &
b1 )
b1 ,
b1 /
b1001 "
b1001 #
#5
b101 !
b101 $
1'
b1001 (
b1011 +
b10 &
b10 )
b10 ,
b10 /
b10 "
b10 #
#6
0'
b110 !
b110 $
1*
b11 &
b11 )
b11 ,
b11 /
b11 "
b11 #
#7
1'
1*
b111 !
b111 $
1-
b1001 +
b110 .
b0 &
b0 )
b0 ,
b0 /
b100 "
b100 #
#8
0'
0*
0-
b1000 !
b1000 $
10
b1 &
b1 )
b1 ,
b1 /
b101 "
b101 #
#9
b1001 !
b1001 $
1'
b10 &
b10 )
b10 ,
b10 /
b110 "
b110 #
